{
    "content": {
        "title": "Scheme for Establishment of Hi-Tech and Mini Dairy Units",
        "state": "Haryana",
        "department": "Department of Animal Husbandry & Dairying",
        "type": "Financial Assistance",
        "beneficiary": "Unemployed persons",
        "details": "The scheme 'Scheme for Establishment of Hi-Tech and Mini Dairy Units' is implemented by the Department of Animal Husbandry & Dairying, Government of Haryana. This is a credit-linked scheme with a primary objective of providing self-employment opportunities. The unemployed persons will be assisted by way of providing financial assistance in the form of subsidies for establishing dairy units of 4, 10, 20, and 50 milch animals like buffaloes, indigenous cows (Hariana, Sahiwal, Belahi, Red Sindhi, Tharparkar, and Gir breeds only) and crossbred cows.",
        "benefits": [
            "25% subsidy on the cost of milch animals for dairy units of 4 and 10 milch animals",
            "Interest subvention on 75% cost of milch animals for dairy units of 20 and 50 milch animals",
            "Financial assistance for livestock insurance",
            "Veterinary health services and training"
        ],
        "eligibility": [
            "Applicant should be 18 to 55 years of age and a resident of Haryana",
            "Applicant must be unemployed",
            "No mandatory educational qualifications or training requirements",
            "Applicant should have space/shed for keeping milch animals",
            "Self-Declaration for being unemployed is required",
            "Specific land requirements for units with 20 and 50 milch animals"
        ],
        "exclusions": [
            "Any group/firm/organization will not be permitted to apply under the Scheme"
        ],
        "application_process": "Online - via Antyodaya-SARAL Portal",
        "documents_required": [
            "Privaar Pahchan Patra (PPP ID)",
            "Copy of Aadhaar Card",
            "Copy of PAN Card",
            "Copy of Bank Passbook or Cancelled Cheque",
            "Photo of Availability of shed/space for keeping animals",
            "Any other documents as required"
        ],
        "faqs": [
            {
                "question": "Who is implementing this scheme?",
                "answer": "The scheme is implemented by the Department of Animal Husbandry & Dairying, Government of Haryana."
            },
            {
                "question": "What types of dairy units can be established under this scheme?",
                "answer": "Dairy units with 4, 10, 20, and 50 milch animals, including buffaloes, indigenous cows, and crossbred cows."
            },
            {
                "question": "What are the medium-term objectives of the scheme?",
                "answer": "To provide gainful self-employment, supplement the income of beneficiaries' families, raise the socio-economic status of weaker sections, and commercialize dairy units."
            },
            {
                "question": "What financial assistance is provided for dairy units of 4 and 10 milch animals?",
                "answer": "A 25% subsidy on the cost of milch animals for loans availed for purchasing these animals."
            },
            {
                "question": "How can eligible applicants apply for the scheme?",
                "answer": "Eligible applicants must apply online through the Antyodaya-SARAL Portal."
            }
        ],
        "sources": [
            {
                "type": "Official Website",
                "url": "https://pashudhanharyana.gov.in/"
            },
            {
                "type": "Guidelines",
                "url": "https://pashudhanharyana.gov.in/sites/default/files/documents/Scheme%202023-24/HTDU%20Scheme.pdf"
            },
            {
                "type": "Antyodaya-SARAL Portal",
                "url": "https://saralharyana.gov.in/"
            }
        ],
        "tags": [
            "Animal Husbandry",
            "Financial Assistance",
            "Hi-Tech",
            "Interest Subvention",
            "Milch Animal",
            "Mini Dairy Unit",
            "Self-employment",
            "Subsidy",
            "Unemployed"
        ]
    }
}